Arquivos/Gereciamento_energetico.sv
// ============================================================
// PROJETO COMPLETO - Gerenciamento_energetico.sv
// ============================================================
// Sistema de gerenciamento energético híbrido (FPGA + BitdogLab)
// ------------------------------------------------------------ 
// Data: 01/11/2025
// FPGA: Lattice ECP5 LFE5U-45F
// ============================================================
// FUNCIONALIDADE GERAL:
// - Joystick controla demanda de potência (LOW/HIGH/IDLE).
// - Botão A → freio regenerativo.
// - Botão B → alterna estado da bateria (cheia/baixa).
// - FPGA devolve código de 3 bits (modo operacional) lido pelo Pico.
// ============================================================

module energy_system_all_in_one (
    input  wire clk,
    input  wire reset_n,

    // Entradas - controle de aceleração / freio (Pico → FPGA)
    input  wire p_demand_low,     // GP18 → A18
    input  wire p_demand_high,    // GP19 → C1
    input  wire p_idle,           // GP20 → B1
    input  wire is_braking,       // GP8  → D2

    // Entrada - botão de bateria (Pico → FPGA)
    input  wire battery_button,   // GP9  → K3 (ativo em LOW)

    // Saídas - modo operacional (FPGA → Pico)
    output wire operating_mode0,  // G20 → GP28 (vermelho)
    output wire operating_mode1,  // L18 → GP16 (verde)
    output wire operating_mode2   // L20 → GP17 (azul)
);

    // ============================================================
    // LÓGICA DE BATERIA CONTROLADA PELO BOTÃO B
    // ============================================================
    // Botão ativo em nível BAIXO:
    // - Pressionado → simula bateria BAIXA → entra em DIESEL_CHARGE (se houver demanda).
    // - Solto → simula bateria CHEIA → opera normalmente no modo elétrico.
    // ============================================================

    wire battery_low  = ~battery_button;  // botão pressionado = bateria fraca
    wire battery_high =  battery_button;  // botão solto = bateria cheia
    wire battery_full =  battery_button;  // mesmo sinal (FSM compatível)

    // ============================================================
    // INSTÂNCIA DO GERENCIADOR DE ENERGIA PRINCIPAL
    // ============================================================
    energy_manager_fixed u_energy (
        .clk(clk),
        .reset_n(reset_n),
        .p_demand_low(p_demand_low),
        .p_demand_high(p_demand_high),
        .p_idle(p_idle),
        .is_braking(is_braking),
        .battery_low(battery_low),
        .battery_high(battery_high),
        .battery_full(battery_full),
        .operating_mode0(operating_mode0),
        .operating_mode1(operating_mode1),
        .operating_mode2(operating_mode2)
    );

endmodule


// ============================================================
// MÓDULO INTERNO: energy_manager_fixed
// ============================================================
// Máquina de estados finita (FSM) que decide o modo de operação
// de um sistema híbrido elétrico/diesel, com recuperação de energia.
// ============================================================

module energy_manager_fixed (
    input  wire clk,
    input  wire reset_n,

    // Entradas
    input  wire p_demand_low,
    input  wire p_demand_high,
    input  wire p_idle,
    input  wire is_braking,
    input  wire battery_low,
    input  wire battery_high,
    input  wire battery_full,

    // Saídas (código de 3 bits do modo operacional)
    output reg operating_mode0,
    output reg operating_mode1,
    output reg operating_mode2
);

    // ============================================================
    // DEFINIÇÃO DOS MODOS
    // ============================================================
    parameter IDLE          = 3'b000;
    parameter ELECTRIC      = 3'b001;
    parameter DIESEL_CHARGE = 3'b010;
    parameter HYBRID_ASSIST = 3'b011;
    parameter REGEN_BRAKING = 3'b100;

    reg [2:0] current_mode, next_mode;

    // ============================================================
    // REGISTRADOR DE ESTADO
    // ============================================================
    always @(posedge clk or negedge reset_n) begin
        if (!reset_n)
            current_mode <= IDLE;
        else
            current_mode <= next_mode;
    end

    // ============================================================
    // LÓGICA DE TRANSIÇÃO DE ESTADOS
    // ============================================================
    always @(*) begin
        next_mode = current_mode;

        case (current_mode)
            //-----------------------------------------------------
            IDLE: begin
                // Bateria cheia → modo elétrico / híbrido normal
                if (p_demand_low && !is_braking && !battery_low)
                    next_mode = ELECTRIC;
                else if (p_demand_high && !is_braking && !battery_low)
                    next_mode = HYBRID_ASSIST;
                // Bateria baixa → só entra em diesel se houver demanda (não parado)
                else if ((p_demand_low || p_demand_high) && battery_low && !is_braking)
                    next_mode = DIESEL_CHARGE;
                else
                    next_mode = IDLE;
            end

            //-----------------------------------------------------
            ELECTRIC: begin
                if (p_demand_high && battery_high)
                    next_mode = HYBRID_ASSIST;
                else if (battery_low)
                    next_mode = DIESEL_CHARGE;
                else if (is_braking)
                    next_mode = REGEN_BRAKING;
                else if (p_idle)
                    next_mode = IDLE;
            end

            //-----------------------------------------------------
            DIESEL_CHARGE: begin
                if (battery_full)
                    next_mode = ELECTRIC;
                else if (is_braking)
                    next_mode = REGEN_BRAKING;
                else if (p_idle)
                    next_mode = IDLE;   // sai do diesel se joystick parado
            end

            //-----------------------------------------------------
            HYBRID_ASSIST: begin
                if (is_braking)
                    next_mode = REGEN_BRAKING;
                else if (battery_low)
                    next_mode = DIESEL_CHARGE;
                else if (p_idle)
                    next_mode = IDLE;
            end

            //-----------------------------------------------------
            REGEN_BRAKING: begin
                if (!is_braking && p_idle)
                    next_mode = IDLE;
                else if (!is_braking && p_demand_low)
                    next_mode = ELECTRIC;
            end

            //-----------------------------------------------------
            default: next_mode = IDLE;
        endcase
    end

    // ============================================================
    // SAÍDAS — codificação direta do estado atual
    // ============================================================
    always @(*) begin
        {operating_mode2, operating_mode1, operating_mode0} = current_mode;
    end

endmodule

Arquivos/tb_energy_system_all_in_one.sv
`timescale 1ns/1ps

module tb_energy_system_all_in_one;

    // Entradas
    reg clk;
    reg reset_n;
    reg p_demand_low;
    reg p_demand_high;
    reg p_idle;
    reg is_braking;
    reg battery_button;

    // Saídas
    wire operating_mode0;
    wire operating_mode1;
    wire operating_mode2;

    // Instância do DUT
    energy_system_all_in_one uut (
        .clk(clk),
        .reset_n(reset_n),
        .p_demand_low(p_demand_low),
        .p_demand_high(p_demand_high),
        .p_idle(p_idle),
        .is_braking(is_braking),
        .battery_button(battery_button),
        .operating_mode0(operating_mode0),
        .operating_mode1(operating_mode1),
        .operating_mode2(operating_mode2)
    );

    // Clock
    initial clk = 0;
    always #5 clk = ~clk;   // 100 MHz

    // Estímulos
    initial begin
        $dumpfile("energy_system_all_in_one.vcd");
        $dumpvars(0, tb_energy_system_all_in_one);

        // Inicialização
        reset_n = 0;
        p_demand_low = 0;
        p_demand_high = 0;
        p_idle = 0;
        is_braking = 0;
        battery_button = 1; // 1 = bateria cheia
        #20;
        reset_n = 1;

        // IDLE
        p_idle = 1; #50;

        // Demanda baixa → elétrico
        p_idle = 0;
        p_demand_low = 1; #80;

        // Alta demanda → híbrido
        p_demand_low = 0;
        p_demand_high = 1; #80;

        // Freio regenerativo
        is_braking = 1; #60;
        is_braking = 0; #40;

        // Bateria fraca
        battery_button = 0;
        p_demand_high = 1; #80;

        // Retorna ao IDLE
        p_demand_high = 0;
        p_idle = 1; #60;

        // Bateria cheia novamente
        battery_button = 1;
        p_idle = 0; p_demand_low = 1; #80;

        // Frenagem novamente
        is_braking = 1; #50;
        is_braking = 0; #50;

        #100;
        $finish;
    end

endmodule

Arquivos/energy_system_all_in_one.vcd
$date
	Thu Nov 06 23:20:45 2025
$end
$version
	Icarus Verilog
$end
$timescale
	1ps
$end
$scope module tb_energy_system_all_in_one $end
$var wire 1 ! operating_mode2 $end
$var wire 1 " operating_mode1 $end
$var wire 1 # operating_mode0 $end
$var reg 1 $ battery_button $end
$var reg 1 % clk $end
$var reg 1 & is_braking $end
$var reg 1 ' p_demand_high $end
$var reg 1 ( p_demand_low $end
$var reg 1 ) p_idle $end
$var reg 1 * reset_n $end
$scope module uut $end
$var wire 1 $ battery_button $end
$var wire 1 + battery_full $end
$var wire 1 , battery_high $end
$var wire 1 - battery_low $end
$var wire 1 % clk $end
$var wire 1 & is_braking $end
$var wire 1 ' p_demand_high $end
$var wire 1 ( p_demand_low $end
$var wire 1 ) p_idle $end
$var wire 1 * reset_n $end
$var wire 1 ! operating_mode2 $end
$var wire 1 " operating_mode1 $end
$var wire 1 # operating_mode0 $end
$scope module u_energy $end
$var wire 1 + battery_full $end
$var wire 1 , battery_high $end
$var wire 1 - battery_low $end
$var wire 1 % clk $end
$var wire 1 & is_braking $end
$var wire 1 ' p_demand_high $end
$var wire 1 ( p_demand_low $end
$var wire 1 ) p_idle $end
$var wire 1 * reset_n $end
$var parameter 3 . DIESEL_CHARGE $end
$var parameter 3 / ELECTRIC $end
$var parameter 3 0 HYBRID_ASSIST $end
$var parameter 3 1 IDLE $end
$var parameter 3 2 REGEN_BRAKING $end
$var reg 3 3 current_mode [2:0] $end
$var reg 3 4 next_mode [2:0] $end
$var reg 1 # operating_mode0 $end
$var reg 1 " operating_mode1 $end
$var reg 1 ! operating_mode2 $end
$upscope $end
$upscope $end
$upscope $end
$enddefinitions $end
$comment Show the parameter values. $end
$dumpall
b100 2
b0 1
b11 0
b1 /
b10 .
$end
#0
$dumpvars
b0 4
b0 3
0-
1,
1+
0*
0)
0(
0'
0&
0%
1$
0#
0"
0!
$end
#5000
1%
#10000
0%
#15000
1%
#20000
0%
1)
1*
#25000
1%
#30000
0%
#35000
1%
#40000
0%
#45000
1%
#50000
0%
#55000
1%
#60000
0%
#65000
1%
#70000
b1 4
0%
1(
0)
#75000
1#
b1 3
1%
#80000
0%
#85000
1%
#90000
0%
#95000
1%
#100000
0%
#105000
1%
#110000
0%
#115000
1%
#120000
0%
#125000
1%
#130000
0%
#135000
1%
#140000
0%
#145000
1%
#150000
b11 4
0%
1'
0(
#155000
1"
b11 3
1%
#160000
0%
#165000
1%
#170000
0%
#175000
1%
#180000
0%
#185000
1%
#190000
0%
#195000
1%
#200000
0%
#205000
1%
#210000
0%
#215000
1%
#220000
0%
#225000
1%
#230000
b100 4
0%
1&
#235000
1!
0"
0#
b100 3
1%
#240000
0%
#245000
1%
#250000
0%
#255000
1%
#260000
0%
#265000
1%
#270000
0%
#275000
1%
#280000
0%
#285000
1%
#290000
0%
0&
#295000
1%
#300000
0%
#305000
1%
#310000
0%
#315000
1%
#320000
0%
#325000
1%
#330000
1-
0%
0,
0+
0$
#335000
1%
#340000
0%
#345000
1%
#350000
0%
#355000
1%
#360000
0%
#365000
1%
#370000
0%
#375000
1%
#380000
0%
#385000
1%
#390000
0%
#395000
1%
#400000
0%
#405000
1%
#410000
b0 4
0%
1)
0'
#415000
0!
b0 3
1%
#420000
0%
#425000
1%
#430000
0%
#435000
1%
#440000
0%
#445000
1%
#450000
0%
#455000
1%
#460000
0%
#465000
1%
#470000
0-
b1 4
0%
1(
0)
1,
1+
1$
#475000
1#
b1 3
1%
#480000
0%
#485000
1%
#490000
0%
#495000
1%
#500000
0%
#505000
1%
#510000
0%
#515000
1%
#520000
0%
#525000
1%
#530000
0%
#535000
1%
#540000
0%
#545000
1%
#550000
b100 4
0%
1&
#555000
1!
0#
b100 3
1%
#560000
0%
#565000
1%
#570000
0%
#575000
1%
#580000
0%
#585000
1%
#590000
0%
#595000
1%
#600000
b1 4
0%
0&
#605000
0!
1#
b1 3
1%
